server_timing/__init__.py
server_timing/middleware.py
server_timing/silk.py
django_server_timing-0.2.0.dist-info/METADATA
django_server_timing-0.2.0.dist-info/WHEEL
django_server_timing-0.2.0.dist-info/licenses/LICENSE
django_server_timing-0.2.0.dist-info/RECORD
